net_prof/__init__.py
net_prof/__main__.py
net_prof/engine (Copy).py
net_prof/engine.py
net_prof/visualize.py
net_prof/data/generate_grouping_rules.py
net_prof-0.1.4.dist-info/METADATA
net_prof-0.1.4.dist-info/WHEEL
net_prof-0.1.4.dist-info/top_level.txt
net_prof-0.1.4.dist-info/RECORD
