Metadata-Version: 2.4
Name: net-prof
Version: 0.1.4
Summary: My cool package
Author-email: Anthony Cardia <acardia@protonmail.com>, Kaushik Velusamy <kaushikvelusamy@gmail.com>
Project-URL: Homepage, https://github.com/argonne-lcf/net-prof
Keywords: network,profiler,cxi,cassini
Classifier: Programming Language :: Python :: 3
Classifier: License :: OSI Approved :: MIT License
Requires-Python: >=3.7
Requires-Dist: numpy
Requires-Dist: matplotlib
